CHANGES.rst
LICENSE.GPL
LICENSE.rst
MANIFEST.in
README.rst
TODO
requirements.txt
setup.cfg
setup.py
jazkarta/__init__.py
jazkarta.shop.egg-info/PKG-INFO
jazkarta.shop.egg-info/SOURCES.txt
jazkarta.shop.egg-info/dependency_links.txt
jazkarta.shop.egg-info/entry_points.txt
jazkarta.shop.egg-info/namespace_packages.txt
jazkarta.shop.egg-info/not-zip-safe
jazkarta.shop.egg-info/requires.txt
jazkarta.shop.egg-info/top_level.txt
jazkarta/shop/__init__.py
jazkarta/shop/api.py
jazkarta/shop/at.py
jazkarta/shop/authnet.py
jazkarta/shop/cart.py
jazkarta/shop/config.py
jazkarta/shop/configure.zcml
jazkarta/shop/interfaces.py
jazkarta/shop/profile.zcml
jazkarta/shop/purchasable.py
jazkarta/shop/setuphandlers.py
jazkarta/shop/ship_ups.py
jazkarta/shop/ship_usps.py
jazkarta/shop/storage.py
jazkarta/shop/stripe.py
jazkarta/shop/utils.py
jazkarta/shop/validators.py
jazkarta/shop/vocabs.py
jazkarta/shop/browser/__init__.py
jazkarta/shop/browser/cart.py
jazkarta/shop/browser/configure.zcml
jazkarta/shop/browser/controlpanel.py
jazkarta/shop/browser/coupons.py
jazkarta/shop/browser/shipping.py
jazkarta/shop/browser/stripe.py
jazkarta/shop/browser/viewlets.py
jazkarta/shop/browser/checkout/__init__.py
jazkarta/shop/browser/checkout/authorize_net_accept_js.py
jazkarta/shop/browser/checkout/authorize_net_sim.py
jazkarta/shop/browser/checkout/stripe.py
jazkarta/shop/browser/checkout/thankyou.py
jazkarta/shop/browser/portlets/__init__.py
jazkarta/shop/browser/portlets/cart_portlet.py
jazkarta/shop/browser/portlets/configure.zcml
jazkarta/shop/browser/portlets/portlet-cart-snippet.pt
jazkarta/shop/browser/static/credit-cards.png
jazkarta/shop/browser/static/jazkarta-shop-compiled.js
jazkarta/shop/browser/static/p4_overlays.js
jazkarta/shop/browser/static/p4_shop.js
jazkarta/shop/browser/static/shop-compiled.css
jazkarta/shop/browser/static/shop-compiled.css.map
jazkarta/shop/browser/static/shop-compiled.js
jazkarta/shop/browser/static/shop-compiled.js.map
jazkarta/shop/browser/static/shop.css
jazkarta/shop/browser/static/shop.js
jazkarta/shop/browser/static/shop.less
jazkarta/shop/browser/templates/add_to_cart.pt
jazkarta/shop/browser/templates/calendar_macros.pt
jazkarta/shop/browser/templates/cart.pt
jazkarta/shop/browser/templates/checkout_cart.pt
