Metadata-Version: 2.1
Name: jazkarta.shop
Version: 2.0.4
Summary: Web-based shop for Plone
Home-page: http://github.com/jazkarta/jazkarta.shop
Author: Jazkarta
Author-email: info@jazkarta.com
License: GPL
Keywords: ecommerce
Platform: UNKNOWN
Classifier: Framework :: Plone
Classifier: Framework :: Plone :: 4.3
Classifier: Framework :: Plone :: 5.1
Classifier: Framework :: Plone :: 5.2
Classifier: Programming Language :: Python
Classifier: Programming Language :: Python :: 2.7
Classifier: Programming Language :: Python :: 3.6
Classifier: Programming Language :: Python :: 3.7
Classifier: Programming Language :: Python :: 3.8
Provides-Extra: test
